armadyl/__init__.py
armadyl/base.py
armadyl/statuses.py
armadyl/util.py
armadyl/version.py
armadyl-0.1.1.dist-info/LICENSE
armadyl-0.1.1.dist-info/METADATA
armadyl-0.1.1.dist-info/WHEEL
armadyl-0.1.1.dist-info/top_level.txt
armadyl-0.1.1.dist-info/zip-safe
armadyl-0.1.1.dist-info/RECORD
